blank_line_after_blocks/__init__.py
blank_line_after_blocks/base_fixer.py
blank_line_after_blocks/helper.py
blank_line_after_blocks/main_jupyter.py
blank_line_after_blocks/main_py.py
blank_line_after_blocks-0.1.4.dist-info/licenses/LICENSE
blank_line_after_blocks-0.1.4.dist-info/METADATA
blank_line_after_blocks-0.1.4.dist-info/WHEEL
blank_line_after_blocks-0.1.4.dist-info/entry_points.txt
blank_line_after_blocks-0.1.4.dist-info/top_level.txt
blank_line_after_blocks-0.1.4.dist-info/RECORD
