Metadata-Version: 2.4
Name: blank-line-after-blocks
Version: 0.1.4
Summary: A Python formatter to automatically add blank lines after if/for/while/with/try blocks
Author-email: Your Name <your.email@example.com>
Maintainer-email: Your Name <your.email@example.com>
License: MIT
Project-URL: Homepage, https://github.com/jsh9/blank-line-after-blocks
Project-URL: Repository, https://github.com/jsh9/blank-line-after-blocks.git
Project-URL: Issues, https://github.com/jsh9/blank-line-after-blocks/issues
Project-URL: Changelog, https://github.com/jsh9/blank-line-after-blocks/blob/main/CHANGELOG.md
Keywords: formatter,code-style,blank-lines,python
Classifier: Development Status :: 4 - Beta
Classifier: Environment :: Console
Classifier: Intended Audience :: Developers
Classifier: License :: OSI Approved :: MIT License
Classifier: Operating System :: OS Independent
Classifier: Programming Language :: Python
Classifier: Programming Language :: Python :: 3
Classifier: Programming Language :: Python :: 3 :: Only
Classifier: Programming Language :: Python :: 3.8
Classifier: Programming Language :: Python :: 3.9
Classifier: Programming Language :: Python :: 3.10
Classifier: Programming Language :: Python :: 3.11
Classifier: Programming Language :: Python :: 3.12
Classifier: Programming Language :: Python :: 3.13
Classifier: Topic :: Software Development :: Libraries :: Python Modules
Classifier: Topic :: Software Development :: Code Generators
Classifier: Topic :: Software Development :: Quality Assurance
Requires-Python: >=3.10
License-File: LICENSE
Requires-Dist: jupyter-notebook-parser>=0.1.4
Requires-Dist: click>=8.0
Provides-Extra: dev
Requires-Dist: pytest>=6.0; extra == "dev"
Requires-Dist: pytest-cov; extra == "dev"
Requires-Dist: mypy; extra == "dev"
Requires-Dist: pre-commit; extra == "dev"
Requires-Dist: tox; extra == "dev"
Provides-Extra: lint
Requires-Dist: flake8>=5.0; extra == "lint"
Requires-Dist: flake8-bugbear; extra == "lint"
Requires-Dist: flake8-comprehensions; extra == "lint"
Requires-Dist: flake8-eradicate; extra == "lint"
Requires-Dist: flake8-broken-line; extra == "lint"
Requires-Dist: flake8-quotes; extra == "lint"
Requires-Dist: flake8-debugger; extra == "lint"
Requires-Dist: flake8-length; extra == "lint"
Requires-Dist: flake8-clean-block; extra == "lint"
Requires-Dist: flake8-indent-in-def; extra == "lint"
Requires-Dist: flake8-picky-parentheses; extra == "lint"
Requires-Dist: flake8-implicit-str-concat; extra == "lint"
Requires-Dist: flake8-return; extra == "lint"
Requires-Dist: flake8-docstrings; extra == "lint"
Provides-Extra: format
Requires-Dist: muff; extra == "format"
Dynamic: license-file
